imephu/__init__.py
imephu/annotation/__init__.py
imephu/annotation/general/__init__.py
imephu/annotation/general/arrow.py
imephu/annotation/general/circle.py
imephu/annotation/general/crosshairs.py
imephu/annotation/general/empty.py
imephu/annotation/general/group.py
imephu/annotation/general/line_path.py
imephu/annotation/general/rectangle.py
imephu/annotation/general/scale_bar.py
imephu/annotation/general/text.py
imephu/annotation/motion.py
imephu/cli.py
imephu/finder_chart.py
imephu/geometry.py
imephu/py.typed
imephu/salt/annotation/__init__.py
imephu/salt/annotation/nir.py
imephu/salt/annotation/rss.py
imephu/salt/annotation/salticam.py
imephu/salt/annotation/telescope.py
imephu/salt/finder_chart.py
imephu/salt/utils.py
imephu/schema.json
imephu/service/horizons.py
imephu/service/survey.py
imephu/utils.py
imephu-0.10.1.dist-info/LICENSE
imephu-0.10.1.dist-info/METADATA
imephu-0.10.1.dist-info/WHEEL
imephu-0.10.1.dist-info/entry_points.txt
imephu-0.10.1.dist-info/RECORD
