Metadata-Version: 2.1
Name: imephu
Version: 0.10.1
Summary: Generate finder charts for astronomical observations.
License: MIT
Author: Southern African Large Telescope
Requires-Python: >=3.8,<4.0
Classifier: License :: OSI Approved :: MIT License
Classifier: Programming Language :: Python :: 3
Classifier: Programming Language :: Python :: 3.8
Classifier: Programming Language :: Python :: 3.9
Classifier: Programming Language :: Python :: 3.10
Classifier: Programming Language :: Python :: 3.11
Classifier: Programming Language :: Python :: 3.12
Requires-Dist: astropy (>=5.0)
Requires-Dist: astroquery (>=0.4.5)
Requires-Dist: defusedxml (>=0.7.1)
Requires-Dist: jsonschema (>=4.4.0)
Requires-Dist: matplotlib (>=3.1,!=3.4.0)
Requires-Dist: pypdf (>=3.17.0,<4.0.0)
Requires-Dist: python-dateutil (>=2.8.2)
Requires-Dist: pyyaml (>=6.0)
Requires-Dist: requests (>=2.27.1)
Requires-Dist: typer[all] (>=0.4.0)
